{
    "Data": {
        "EnableSaving": true,
        "Objectives": [
            {
                "Id": "c2b3f8e3-0eaf-41b3-8b8c-3cf012a1d0bc",
                "Primary": true,
                "IsHidden": true,
                "SuccessEvent": {
                    "EventName": "Kill",
                    "EventValues": {
                        "RepositoryId": "63283fb2-a653-486d-a505-e471efbc8c54"
                    }
                }
            }
        ],
        "Entrances": ["f1de2373-eebe-4448-808a-8c2764b2c931"],
        "Bricks": [
            "assembly:/_pro/scenes/missions/miami/mission_sambuca.brick"
        ],
        "Stashpoints": [],
        "VR": [
            {
                "Quality": "base",
                "Bricks": [
                    "assembly:/_pro/Scenes/Bricks/vr_setup.brick",
                    "assembly:/_pro/scenes/missions/miami/vr_overrides_flamingo.brick",
                    "assembly:/_PRO/scenes/missions/miami/vr_overrides_ps4perf.brick"
                ]
            },
            {
                "Quality": "better",
                "Bricks": [
                    "assembly:/_pro/Scenes/Bricks/vr_setup.brick",
                    "assembly:/_pro/scenes/missions/miami/vr_overrides_flamingo.brick"
                ]
            }
        ],
        "GameChangers": ["b43f84f7-6c26-4adf-b74a-6d598f03cbe3"]
    },
    "Metadata": {
        "Id": "95ee5b1b-12ba-4235-8a0a-2cd27aaf179e",
        "Title": "UI_PEACOCK_KASTURI2",
        "Description": "UI_CONTRACT_SAMBUCA_DESC",
        "BriefingVideo": "briefing_sambuca",
        "DebriefingVideo": "debriefing_sambuca",
        "CodeName_Hint": "Arcade Kasturi Sambuca",
        "ScenePath": "assembly:/_pro/scenes/missions/miami/scene_et_sambuca.entity",
        "TileImage": "images/contracts/elusive/046_sambuca/Title.jpg",
        "Location": "LOCATION_MIAMI",
        "CreatorUserId": "fadb923c-e6bb-4283-a537-eb4d1150262e",
        "Type": "arcade",
        "Entitlements": ["LOCATION_GOLDEN"],
        "InGroup": "797e204a-ef3d-463b-a386-57df0fe29b8f",
        "GroupObjectiveDisplayOrder": [
            { "Id": "b43f84f7-6c26-4adf-b74a-6d598f03cbe3" },
            { "Id": "c2b3f8e3-0eaf-41b3-8b8c-3cf012a1d0bc" }
        ]
    },
    "UserData": {}
}
